LICENSE
README.md
pyproject.toml
setup.cfg
setup.py
examples/alipay/__init__.py
examples/alipay/main.py
examples/aliyun/__init__.py
examples/aliyun/main.py
examples/doudian/__init__.py
examples/doudian/main.py
examples/feishu/__init__.py
examples/feishu/bot.py
examples/feishu/sheet.py
examples/lenovo/__init__.py
examples/lenovo/pay.py
examples/lenovo/query.py
examples/lenovo/sign.py
examples/sms/__init__.py
examples/sms/main.py
examples/sms/wgws.py
examples/tanmarket/__init__.py
examples/tanmarket/bulk_gonghai.py
examples/tanmarket/create.py
examples/tanmarket/field_map.py
examples/tanmarket/query.py
examples/tanmarket/update.py
examples/wechat/__init__.py
examples/wechat/channels.py
examples/wechat/decrypt.py
examples/wechat/oauth.py
examples/wechat/open.py
examples/wechat/pay.py
examples/xhs/__init__.py
examples/xhs/main.py
examples/xiaoetong/__init__.py
examples/xiaoetong/main.py
examples/yizhi/__init__.py
examples/yizhi/api.py
examples/yizhi/query.py
examples/yunduo/__init__.py
examples/yunduo/main.py
openapi/__init__.py
openapi/enums.py
openapi/exceptions.py
openapi/utils.py
openapi/providers/__init__.py
openapi/providers/alipay.py
openapi/providers/aliyun.py
openapi/providers/base.py
openapi/providers/doudian.py
openapi/providers/generic.py
openapi/providers/lenovo.py
openapi/providers/polyv.py
openapi/providers/xhs.py
openapi/providers/xiaoetong.py
openapi/providers/yizhi.py
openapi/providers/crm/__init__.py
openapi/providers/crm/tanmarket.py
openapi/providers/crm/yunduo.py
openapi/providers/feishu/__init__.py
openapi/providers/feishu/bot.py
openapi/providers/feishu/open.py
openapi/providers/sms/__init__.py
openapi/providers/sms/submail.py
openapi/providers/sms/wgws.py
openapi/providers/wechat/__init__.py
openapi/providers/wechat/open.py
openapi/providers/wechat/pay.py
openapipy.egg-info/PKG-INFO
openapipy.egg-info/SOURCES.txt
openapipy.egg-info/dependency_links.txt
openapipy.egg-info/requires.txt
openapipy.egg-info/top_level.txt
openapipy.egg-info/zip-safe
tests/__init__.py
tests/test_ali.py
tests/test_feishu.py
tests/test_xiaoetong.py