Metadata-Version: 2.4
Name: openapipy
Version: 0.12.1
Summary: openapi tools
Home-page: https://github.com/luffy-genius/openapi
Author: ZhiChaoLiu
Author-email: liuzhichao9527@gmail.com
License: MIT
Keywords: openapi,openapi-python,python-openapi,openapipy,pyopenapi
License-File: LICENSE
Requires-Dist: httpx
Requires-Dist: pydantic
Requires-Dist: pycryptodome
Requires-Dist: cryptography
Dynamic: author
Dynamic: author-email
Dynamic: description
Dynamic: description-content-type
Dynamic: home-page
Dynamic: keywords
Dynamic: license
Dynamic: license-file
Dynamic: requires-dist
Dynamic: summary
